quacker/__init__.py
quacker/cli.py
quacker/config/QuackerConfigParser.py
quacker/config/__init__.py
quacker/databases/BigQueryConnector.py
quacker/databases/DuckDBConnector.py
quacker/databases/QueryGenerator.py
quacker/databases/SnowflakeConnector.py
quacker/databases/__init__.py
quacker/dbt/DbtAdapterInstaller.py
quacker/dbt/DbtManifestParser.py
quacker/dbt/DbtProfilesParser.py
quacker/dbt/DbtProjectParser.py
quacker/dbt/__init__.py
quacker-0.7.2.dist-info/METADATA
quacker-0.7.2.dist-info/WHEEL
quacker-0.7.2.dist-info/entry_points.txt
quacker-0.7.2.dist-info/top_level.txt
quacker-0.7.2.dist-info/RECORD
