Metadata-Version: 2.1
Name: quacker
Version: 0.7.2
Summary: Sync dbt sources and models from cloud warehouses to duckdb
Author: Amir Jaber
Requires-Dist: pandas <3.0.0,>=1.5.0
Requires-Dist: snowflake-connector-python <4.0.0,>=2.1.0
Requires-Dist: pyarrow <15.0.0,>=12.0.0
Requires-Dist: duckdb <0.10.0,>=0.9.0
Requires-Dist: db-dtypes <2.0.0,>=1.1.0
Requires-Dist: pyyaml <7.0.0,>=6.0.0
Requires-Dist: google-cloud-bigquery <4.0.0,>=3.5.0
